cubicweb_rq/__init__.py
cubicweb_rq/__pkginfo__.py
cubicweb_rq/ccplugin.py
cubicweb_rq/entities.py
cubicweb_rq/hooks.py
cubicweb_rq/rq.py
cubicweb_rq/schema.py
cubicweb_rq/views.py
cubicweb_rq/i18n/en.po
cubicweb_rq/i18n/es.po
cubicweb_rq/i18n/fr.po
cubicweb_rq/migration/postcreate.py
cubicweb_rq-0.1.1.dist-info/METADATA
cubicweb_rq-0.1.1.dist-info/WHEEL
cubicweb_rq-0.1.1.dist-info/entry_points.txt
cubicweb_rq-0.1.1.dist-info/top_level.txt
cubicweb_rq-0.1.1.dist-info/RECORD
