Metadata-Version: 2.1
Name: cubicweb-rq
Version: 0.1.1
Summary: Cube for starting RqJobs on a Rq worker
Home-page: https://forge.extranet.logilab.fr/cubicweb/cubes/rq
Author: LOGILAB S.A. (Paris, FRANCE)
Author-email: contact@logilab.fr
License: LGPL
Classifier: Environment :: Web Environment
Classifier: Framework :: CubicWeb
Classifier: Programming Language :: Python :: 3
Classifier: Programming Language :: JavaScript
Requires-Dist: cubicweb <5.0.0,>=4.5.2
Requires-Dist: pyramid-session-redis <2.0.0,>=1.6.3
Requires-Dist: rq <2.0.0
Provides-Extra: dev
Requires-Dist: fakeredis ; extra == 'dev'
Requires-Dist: pytest ; extra == 'dev'
Requires-Dist: webtest ; extra == 'dev'
